
[
    {
      "title": "Project 1",
      "description": "Description for Project 1",
      "hrefSite": "https://",
      "hrefGitHub": "https://",
      "imageSrc": "",
      "imageAlt": ""
    },
    {
      "title": "Twain and Company Bookstore",
      "description": [
        "Integrates ReactDOM.createPortal to implement a shopping cart modal",
        "Employs useContext and useReducer for cart management, and useRef for focus control",
        "Firebase backend implementation",
        "Accessibility-first approach with skip-to-content button, color contrast, button focus, focus outline, modal access via keyboard, and",
        "aria-live triggered by cart updates"
        ],
      "hrefSite": "https://",
      "hrefGitHub": "https://",
      "imageSrc": "",
      "imageAlt": ""
    },
    {
      "title": "Project 3",
      "description": "Description for Project 3",
      "hrefSite": "https://",
      "hrefGitHub": "https://",
      "imageSrc": "",
      "imageAlt": ""
    }
  ]
  